igor331/__init__.py
igor331/mille.py
igor331/numeri.py
igor331/oggi3.py
igor331/oggi_ita.py
igor331/pd_header.py
igor331/pd_mille.py
igor331/prova331.py
igor331/pulisci_chr.py
igor331/stampa_under.py
igor331/tag.py
igor331-12.dist-info/LICENSE.txt
igor331-12.dist-info/METADATA
igor331-12.dist-info/WHEEL
igor331-12.dist-info/top_level.txt
igor331-12.dist-info/RECORD
