Metadata-Version: 2.1
Name: igor331
Version: 12
Summary: package generale per Pyhton
Author: Igor Bonat
Author-email: <igorbonat@gmail.com>
Keywords: python,esempio package
Classifier: Development Status :: 3 - Alpha
Classifier: Intended Audience :: Education
Classifier: Programming Language :: Python :: 3
Classifier: Operating System :: MacOS :: MacOS X
Classifier: Operating System :: Microsoft :: Windows
License-File: LICENSE.txt
Requires-Dist: pandas
Requires-Dist: numpy
